paretobench/__init__.py
paretobench/analyze_metrics.py
paretobench/cf.py
paretobench/containers.py
paretobench/ctp.py
paretobench/dtlz.py
paretobench/dtlz_utils.py
paretobench/exceptions.py
paretobench/factory.py
paretobench/metrics.py
paretobench/misc.py
paretobench/problem.py
paretobench/simple_serialize.py
paretobench/utils.py
paretobench/wfg.py
paretobench/wfg_utils.py
paretobench/zdt.py
paretobench-0.1.0.dist-info/LICENSE
paretobench-0.1.0.dist-info/METADATA
paretobench-0.1.0.dist-info/WHEEL
paretobench-0.1.0.dist-info/top_level.txt
paretobench-0.1.0.dist-info/RECORD
