Metadata-Version: 2.1
Name: paretobench
Version: 0.1.0
Summary: A collection of multiobjective optimization test problems.
Author-email: "Christopher M. Pierce" <contact@chris-pierce.com>
License: BSD 3-Clause License
Project-URL: Homepage, https://github.com/electronsandstuff/ParetoBench
Project-URL: Repository, https://github.com/electronsandstuff/ParetoBench
Classifier: Programming Language :: Python :: 3
Classifier: Operating System :: OS Independent
Classifier: License :: OSI Approved :: BSD License
Requires-Python: >=3.9
License-File: LICENSE
Requires-Dist: numpy
Requires-Dist: matplotlib
Requires-Dist: pydantic
Requires-Dist: h5py
Requires-Dist: pandas
Requires-Dist: scipy
Requires-Dist: jinja2
